README.md
setup.py
listfun/__init__.py
listfun/listfun.py
listfun.egg-info/PKG-INFO
listfun.egg-info/SOURCES.txt
listfun.egg-info/dependency_links.txt
listfun.egg-info/not-zip-safe
listfun.egg-info/top_level.txt