Metadata-Version: 1.0
Name: listfun
Version: 1.0
Summary: List functions https://github.com/kgraghav/Listfun/
Home-page: UNKNOWN
Author: UNKNOWN
Author-email: UNKNOWN
License: UNKNOWN
Platform: UNKNOWN
